setup.py
at/__init__.py
at.egg-info/PKG-INFO
at.egg-info/SOURCES.txt
at.egg-info/dependency_links.txt
at.egg-info/entry_points.txt
at.egg-info/top_level.txt