Metadata-Version: 1.1
Name: at
Version: 0.0.2
Summary: A set of utilities I use frequently in interactive environments
Home-page: https://github.com/lahwran/dotfiles/tree/master/packages/at
Author: lahwran
Author-email: lahwran0@gmail.com
License: MIT
Keywords: utility
Platform: UNKNOWN
Classifier: Development Status :: 3 - Alpha
Classifier: Topic :: Utilities
Classifier: License :: OSI Approved :: MIT License
